cdk_secrets/__init__.py
cdk_secrets/py.typed
cdk_secrets/_jsii/__init__.py
cdk_secrets/_jsii/cdk-secrets@0.4.9.jsii.tgz
cdk_secrets-0.4.9.dist-info/METADATA
cdk_secrets-0.4.9.dist-info/WHEEL
cdk_secrets-0.4.9.dist-info/top_level.txt
cdk_secrets-0.4.9.dist-info/RECORD
