Metadata-Version: 2.1
Name: cdk-secrets
Version: 0.4.9
Summary: CDK Construct for secrets
Home-page: https://github.com/udondan/cdk-secrets
Author: Daniel Schroeder
License: MIT
Project-URL: Source, https://github.com/udondan/cdk-secrets.git
Platform: UNKNOWN
Classifier: Intended Audience :: Developers
Classifier: Operating System :: OS Independent
Classifier: Programming Language :: JavaScript
Classifier: Programming Language :: Python :: 3 :: Only
Classifier: Programming Language :: Python :: 3.6
Classifier: Programming Language :: Python :: 3.7
Classifier: Programming Language :: Python :: 3.8
Classifier: Typing :: Typed
Classifier: Development Status :: 4 - Beta
Classifier: License :: OSI Approved
Requires-Python: >=3.6
Requires-Dist: jsii (~=0.22.0)
Requires-Dist: publication (>=0.0.3)
Requires-Dist: aws-cdk.aws-cloudformation (<2.0.0,>=1.24.0)
Requires-Dist: aws-cdk.aws-iam (<2.0.0,>=1.24.0)
Requires-Dist: aws-cdk.aws-kms (<2.0.0,>=1.24.0)
Requires-Dist: aws-cdk.aws-lambda (<2.0.0,>=1.24.0)
Requires-Dist: aws-cdk.aws-s3 (<2.0.0,>=1.24.0)
Requires-Dist: aws-cdk.core (<2.0.0,>=1.24.0)
